qt5_applications-5.15.2.2.1.data/purelib/qt5_applications/__init__.py
qt5_applications-5.15.2.2.1.data/purelib/qt5_applications/_applications.py
qt5_applications-5.15.2.2.1.data/purelib/qt5_applications/_version.py
qt5_applications-5.15.2.2.1.data/purelib/qt5_applications/Qt/bin/assistant
qt5_applications-5.15.2.2.1.data/purelib/qt5_applications/Qt/bin/canbusutil
qt5_applications-5.15.2.2.1.data/purelib/qt5_applications/Qt/bin/designer
qt5_applications-5.15.2.2.1.data/purelib/qt5_applications/Qt/bin/lconvert
qt5_applications-5.15.2.2.1.data/purelib/qt5_applications/Qt/bin/licheck64
qt5_applications-5.15.2.2.1.data/purelib/qt5_applications/Qt/bin/linguist
qt5_applications-5.15.2.2.1.data/purelib/qt5_applications/Qt/bin/lprodump
qt5_applications-5.15.2.2.1.data/purelib/qt5_applications/Qt/bin/lrelease
qt5_applications-5.15.2.2.1.data/purelib/qt5_applications/Qt/bin/lrelease-pro
qt5_applications-5.15.2.2.1.data/purelib/qt5_applications/Qt/bin/lupdate
qt5_applications-5.15.2.2.1.data/purelib/qt5_applications/Qt/bin/lupdate-pro
qt5_applications-5.15.2.2.1.data/purelib/qt5_applications/Qt/bin/moc
qt5_applications-5.15.2.2.1.data/purelib/qt5_applications/Qt/bin/pixeltool
qt5_applications-5.15.2.2.1.data/purelib/qt5_applications/Qt/bin/qcollectiongenerator
qt5_applications-5.15.2.2.1.data/purelib/qt5_applications/Qt/bin/qdbus
qt5_applications-5.15.2.2.1.data/purelib/qt5_applications/Qt/bin/qdbuscpp2xml
qt5_applications-5.15.2.2.1.data/purelib/qt5_applications/Qt/bin/qdbusviewer
qt5_applications-5.15.2.2.1.data/purelib/qt5_applications/Qt/bin/qdbusxml2cpp
qt5_applications-5.15.2.2.1.data/purelib/qt5_applications/Qt/bin/qdistancefieldgenerator
qt5_applications-5.15.2.2.1.data/purelib/qt5_applications/Qt/bin/qdoc
qt5_applications-5.15.2.2.1.data/purelib/qt5_applications/Qt/bin/qgltf
qt5_applications-5.15.2.2.1.data/purelib/qt5_applications/Qt/bin/qhelpgenerator
qt5_applications-5.15.2.2.1.data/purelib/qt5_applications/Qt/bin/qlalr
qt5_applications-5.15.2.2.1.dist-info/COPYING
qt5_applications-5.15.2.2.1.dist-info/METADATA
qt5_applications-5.15.2.2.1.dist-info/WHEEL
qt5_applications-5.15.2.2.1.dist-info/top_level.txt
qt5_applications-5.15.2.2.1.dist-info/RECORD
